juvio/__init__.py
juvio/content_manager.py
juvio/converter.py
juvio/kernel_launcher.py
juvio/server_extension.py
juvio/shared.py
juvio/kernelspec/kernel.json
juvio/labextension/package.json
juvio/labextension/static/509.8b21d569ebbb8f039bdd.js
juvio/labextension/static/728.864a8d7732d3e14d284a.js
juvio/labextension/static/remoteEntry.cb75fcc929fa00484f36.js
juvio/labextension/static/style.js
juvio/labextension/static/third-party-licenses.json
juvio-0.1.0b2.data/data/share/jupyter/kernels/juvio/kernel.json
juvio-0.1.0b2.data/data/share/jupyter/labextensions/juvio_frontend/package.json
juvio-0.1.0b2.data/data/share/jupyter/labextensions/juvio_frontend/static/509.8b21d569ebbb8f039bdd.js
juvio-0.1.0b2.data/data/share/jupyter/labextensions/juvio_frontend/static/728.864a8d7732d3e14d284a.js
juvio-0.1.0b2.data/data/share/jupyter/labextensions/juvio_frontend/static/remoteEntry.cb75fcc929fa00484f36.js
juvio-0.1.0b2.data/data/share/jupyter/labextensions/juvio_frontend/static/third-party-licenses.json
juvio-0.1.0b2.dist-info/METADATA
juvio-0.1.0b2.dist-info/WHEEL
juvio-0.1.0b2.dist-info/entry_points.txt
juvio-0.1.0b2.dist-info/top_level.txt
juvio-0.1.0b2.dist-info/RECORD
